nsgt/__init__.py
nsgt/_nsgtf_loop.cpython-310-darwin.so
nsgt/_nsigtf_loop.cpython-310-darwin.so
nsgt/audio.py
nsgt/cq.py
nsgt/fft.py
nsgt/fscale.py
nsgt/nsdual.py
nsgt/nsgfwin.py
nsgt/nsgfwin_sl.py
nsgt/nsgtf.py
nsgt/nsgtf_loop.py
nsgt/nsigtf.py
nsgt/nsigtf_loop.py
nsgt/reblock.py
nsgt/slicing.py
nsgt/slicq.py
nsgt/unslicing.py
nsgt/util.py
nsgt-0.19.dist-info/LICENSE
nsgt-0.19.dist-info/METADATA
nsgt-0.19.dist-info/WHEEL
nsgt-0.19.dist-info/pbr.json
nsgt-0.19.dist-info/top_level.txt
nsgt-0.19.dist-info/RECORD
