Metadata-Version: 2.1
Name: nsgt
Version: 0.19
Summary: Python implementation of Non-Stationary Gabor Transform (NSGT)
Home-page: http://grrrr.org/nsgt
Author: Thomas Grill
Author-email: gr@grrrr.org
Maintainer: Thomas Grill
Maintainer-email: gr@grrrr.org
License: Artistic License
Keywords: fourier gabor
Platform: UNKNOWN
Classifier: Development Status :: 4 - Beta
Classifier: Topic :: Scientific/Engineering :: Mathematics
Classifier: License :: OSI Approved :: Artistic License
Classifier: Programming Language :: Python
Requires: numpy
License-File: LICENSE
